pystk2_gymnasium/__init__.py
pystk2_gymnasium/_version.py
pystk2_gymnasium/definitions.py
pystk2_gymnasium/envs.py
pystk2_gymnasium/pystk_process.py
pystk2_gymnasium/stk_wrappers.py
pystk2_gymnasium/utils.py
pystk2_gymnasium/vecenv.py
pystk2_gymnasium/wrappers.py
pystk2_gymnasium/cli/__init__.py
pystk2_gymnasium/cli/race.py
pystk2_gymnasium/cli/race_client.py
pystk2_gymnasium/cli/race_protocol.py
pystk2_gymnasium/cli/race_server.py
pystk2_gymnasium/cli/stk_graph.py
pystk2_gymnasium-0.8.4.dist-info/METADATA
pystk2_gymnasium-0.8.4.dist-info/WHEEL
pystk2_gymnasium-0.8.4.dist-info/entry_points.txt
pystk2_gymnasium-0.8.4.dist-info/licenses/LICENSE
pystk2_gymnasium-0.8.4.dist-info/RECORD
