Metadata-Version: 2.4
Name: pystk2-gymnasium
Version: 0.8.4
Summary: Gymnasium wrapper for PySTK2
Project-URL: Homepage, https://github.com/bpiwowar/pystk2-gymnasium
Project-URL: Repository, https://github.com/bpiwowar/pystk2-gymnasium
Project-URL: Changelog, https://github.com/bpiwowar/pystk2-gymnasium/blob/main/CHANGELOG.md
Author-email: Benjamin Piwowarski <benjamin@piwowarski.fr>
License-Expression: GPL-3.0-or-later
License-File: LICENSE
Classifier: Development Status :: 3 - Alpha
Classifier: Intended Audience :: Developers
Classifier: License :: OSI Approved :: GNU General Public License v3 or later (GPLv3+)
Classifier: Programming Language :: Python :: 3
Classifier: Programming Language :: Python :: 3.10
Classifier: Programming Language :: Python :: 3.11
Classifier: Programming Language :: Python :: 3.12
Requires-Python: >=3.10
Requires-Dist: gymnasium>0.29.0
Requires-Dist: numba
Requires-Dist: pysupertuxkart2>=0.6.2
Provides-Extra: cli
Requires-Dist: torch; extra == 'cli'
Requires-Dist: tqdm; extra == 'cli'
Provides-Extra: record
Requires-Dist: moviepy; extra == 'record'
Provides-Extra: remote
Requires-Dist: pyzmq>=25; extra == 'remote'
Provides-Extra: web
Requires-Dist: dash; extra == 'web'
Requires-Dist: plotly; extra == 'web'
